<?xml version="1.0" encoding="utf-8"?>
<LanguageData>
  <!--The following translations were generated by https://www.deepl.com/-->
  <!-- EN: charge shot -->
  <HRACA_Bullet_ChargeBR.label>冲锋枪</HRACA_Bullet_ChargeBR.label>
  <HRACA_Bullet_ChargeDMR.label>冲锋枪</HRACA_Bullet_ChargeDMR.label>
  <HRACA_Bullet_ChargeMagnum.label>冲锋枪</HRACA_Bullet_ChargeMagnum.label>
  <HRACA_Bullet_ChargePistol.label>冲锋枪</HRACA_Bullet_ChargePistol.label>
  <!-- EN: charge rocket -->
  <HRACA_Bullet_ChargeRocket.label>冲锋火箭</HRACA_Bullet_ChargeRocket.label>
  <HRACA_Bullet_ChargeShotgun.label>冲锋枪</HRACA_Bullet_ChargeShotgun.label>
  <HRACA_Bullet_ChargeSMG.label>冲锋枪</HRACA_Bullet_ChargeSMG.label>
  <HRACA_Bullet_ChargeSniperRifle.label>冲锋枪</HRACA_Bullet_ChargeSniperRifle.label>
  <!-- EN: EMP launcher shell -->
  <HRACA_Bullet_EMPLauncher.label>EMP 发射器外壳</HRACA_Bullet_EMPLauncher.label>
  <!-- EN: EMP grenade launcher -->
  <HRACA_EmpLauncher.label>EMP 榴弹发射器</HRACA_EmpLauncher.label>
  <!-- EN: A short-barreled EMP shell launcher. The shell will upon impact release a burst of electromagnetic energy, stunning mechanical targets (mechanoids, turrets, mortars) and depleting shields in the area of effect. -->
  <HRACA_EmpLauncher.description>短管 EMP 炮弹发射器。炮弹在撞击时会释放出一阵电磁能量，使机械目标（机械人、炮塔、迫击炮）眩晕，并消耗影响范围内的护盾。</HRACA_EmpLauncher.description>
  <!-- EN: stock -->
  <HRACA_EmpLauncher.tools.stock.label>库存</HRACA_EmpLauncher.tools.stock.label>
  <!-- EN: barrel -->
  <HRACA_EmpLauncher.tools.barrel.label>桶</HRACA_EmpLauncher.tools.barrel.label>
  <HRACA_EmpLauncher.verbs.Verb_Shoot.label>EMP 榴弹发射器</HRACA_EmpLauncher.verbs.Verb_Shoot.label>
  <!-- EN: charge battle rifle -->
  <HRACA_Gun_Charge_BR.label>冲锋战斗步枪</HRACA_Gun_Charge_BR.label>
  <!-- EN: A three shot burst, long ranged, charged-shot battle rifle. Perfect for use against armored targets at mid range. Each shot is charged with unstable energy as it leaves the barrel. Released on impact, the charged energy greatly increases the damage done. -->
  <HRACA_Gun_Charge_BR.description>三连发、远程、充能射击的战斗步枪。非常适合在中距离对付装甲目标。每一发子弹在离开枪管时都会充满不稳定的能量。撞击时释放的充能可大大增加伤害。</HRACA_Gun_Charge_BR.description>
  <HRACA_Gun_Charge_BR.tools.stock.label>库存</HRACA_Gun_Charge_BR.tools.stock.label>
  <HRACA_Gun_Charge_BR.tools.barrel.label>桶</HRACA_Gun_Charge_BR.tools.barrel.label>
  <!-- EN: grip -->
  <HRACA_Gun_Charge_BR.tools.grip.label>握把</HRACA_Gun_Charge_BR.tools.grip.label>
  <HRACA_Gun_Charge_BR.verbs.Verb_Shoot.label>冲锋战斗步枪</HRACA_Gun_Charge_BR.verbs.Verb_Shoot.label>
  <!-- EN: charge marksman rifle -->
  <HRACA_Gun_Charge_DMR.label>冲锋神枪</HRACA_Gun_Charge_DMR.label>
  <!-- EN: A one shot, long ranged, charged-shot marksman rifle. Perfect for use against armored targets at mid range. Each shot is charged with unstable energy as it leaves the barrel. Released on impact, the charged energy greatly increases the damage done. -->
  <HRACA_Gun_Charge_DMR.description>一发远距离冲锋枪。非常适合在中距离对付装甲目标。每一发子弹在离开枪管时都充满了不稳定的能量。撞击时释放的充能可大大增加伤害。</HRACA_Gun_Charge_DMR.description>
  <HRACA_Gun_Charge_DMR.tools.stock.label>库存</HRACA_Gun_Charge_DMR.tools.stock.label>
  <HRACA_Gun_Charge_DMR.tools.barrel.label>桶</HRACA_Gun_Charge_DMR.tools.barrel.label>
  <HRACA_Gun_Charge_DMR.tools.grip.label>握把</HRACA_Gun_Charge_DMR.tools.grip.label>
  <HRACA_Gun_Charge_DMR.verbs.Verb_Shoot.label>冲锋神枪</HRACA_Gun_Charge_DMR.verbs.Verb_Shoot.label>
  <!-- EN: charge launcher -->
  <HRACA_Gun_Charge_Launcher.label>装药发射器</HRACA_Gun_Charge_Launcher.label>
  <!-- EN: A charge launcher, shooting two charge rockets after each other. Each rocket is charged with unstable energy as it leaves the barrel. Released on impact, the charged energy greatly increases the damage done by the explosion. -->
  <HRACA_Gun_Charge_Launcher.description>装药发射器，可发射两枚装药火箭弹。每枚火箭弹在离开炮管时都充入了不稳定的能量。撞击时释放的充能可大大增加爆炸造成的伤害。</HRACA_Gun_Charge_Launcher.description>
  <HRACA_Gun_Charge_Launcher.tools.stock.label>库存</HRACA_Gun_Charge_Launcher.tools.stock.label>
  <HRACA_Gun_Charge_Launcher.tools.barrel.label>桶</HRACA_Gun_Charge_Launcher.tools.barrel.label>
  <HRACA_Gun_Charge_Launcher.tools.grip.label>握把</HRACA_Gun_Charge_Launcher.tools.grip.label>
  <HRACA_Gun_Charge_Launcher.verbs.Verb_ShootOneUse.label>装药发射器</HRACA_Gun_Charge_Launcher.verbs.Verb_ShootOneUse.label>
  <!-- EN: charge magnum -->
  <HRACA_Gun_Charge_Magnum.label>冲锋枪</HRACA_Gun_Charge_Magnum.label>
  <!-- EN: A powerful charge pistol, sacrificing neither damage, accuracy or range. Extremely rare and hard to build. Each shot is charged with unstable energy as it leaves the barrel. Released on impact, the charged energy greatly increases the damage done. -->
  <HRACA_Gun_Charge_Magnum.description>威力强大的冲锋手枪，既不牺牲伤害，也不牺牲精度或射程。极其稀有，难以制造。每一发子弹在离开枪管时都会充满不稳定的能量。在撞击时释放，带电能量会大大增加造成的伤害。</HRACA_Gun_Charge_Magnum.description>
  <HRACA_Gun_Charge_Magnum.tools.barrel.label>桶</HRACA_Gun_Charge_Magnum.tools.barrel.label>
  <HRACA_Gun_Charge_Magnum.tools.grip.label>握把</HRACA_Gun_Charge_Magnum.tools.grip.label>
  <HRACA_Gun_Charge_Magnum.verbs.Verb_Shoot.label>冲锋枪</HRACA_Gun_Charge_Magnum.verbs.Verb_Shoot.label>
  <!-- EN: charge tactical pistol -->
  <HRACA_Gun_Charge_Pistol.label>冲锋战术手枪</HRACA_Gun_Charge_Pistol.label>
  <!-- EN: A fully automatic charge pistol, sacrificing damage for long range and accuracy. Each shot is charged with unstable energy as it leaves the barrel. Released on impact, the charged energy greatly increases the damage done. -->
  <HRACA_Gun_Charge_Pistol.description>全自动冲锋手枪，牺牲伤害以换取远距离和精确度。每一发子弹在离开枪管时都会充满不稳定的能量。撞击时释放的充能可大大增加伤害。</HRACA_Gun_Charge_Pistol.description>
  <HRACA_Gun_Charge_Pistol.tools.barrel.label>桶</HRACA_Gun_Charge_Pistol.tools.barrel.label>
  <HRACA_Gun_Charge_Pistol.tools.grip.label>握把</HRACA_Gun_Charge_Pistol.tools.grip.label>
  <HRACA_Gun_Charge_Pistol.verbs.Verb_Shoot.label>冲锋战术手枪</HRACA_Gun_Charge_Pistol.verbs.Verb_Shoot.label>
  <!-- EN: charge quickfire rifle -->
  <HRACA_Gun_Charge_Rifle.label>冲锋速射步枪</HRACA_Gun_Charge_Rifle.label>
  <!-- EN: A quickfire charged-shot assault rifle. Each shot is charged with unstable energy as it leaves the barrel. Released on impact, the charged energy greatly increases the damage done. -->
  <HRACA_Gun_Charge_Rifle.description>快速充能射击突击步枪。每一发子弹在离开枪管时都充满了不稳定的能量。在撞击时释放，带电能量会大大增加造成的伤害。</HRACA_Gun_Charge_Rifle.description>
  <HRACA_Gun_Charge_Rifle.tools.stock.label>库存</HRACA_Gun_Charge_Rifle.tools.stock.label>
  <HRACA_Gun_Charge_Rifle.tools.barrel.label>桶</HRACA_Gun_Charge_Rifle.tools.barrel.label>
  <HRACA_Gun_Charge_Rifle.verbs.Verb_Shoot.label>冲锋速射步枪</HRACA_Gun_Charge_Rifle.verbs.Verb_Shoot.label>
  <!-- EN: charge tactical shotgun -->
  <HRACA_Gun_Charge_Shotgun.label>冲锋战术霰弹枪</HRACA_Gun_Charge_Shotgun.label>
  <!-- EN: A deadly, charged-shot shotgun. It sacrifices range and accuracy for damage at close range. Each shot is charged with unstable energy as it leaves the barrel. Released on impact, the charged energy greatly increases the damage done. -->
  <HRACA_Gun_Charge_Shotgun.description>致命的充能霰弹枪。它牺牲了射程和精度，却能在近距离造成伤害。每一发子弹在离开枪管时都充满了不稳定的能量。在撞击时释放，带电能量会大大增加造成的伤害。</HRACA_Gun_Charge_Shotgun.description>
  <HRACA_Gun_Charge_Shotgun.tools.stock.label>库存</HRACA_Gun_Charge_Shotgun.tools.stock.label>
  <HRACA_Gun_Charge_Shotgun.tools.barrel.label>桶</HRACA_Gun_Charge_Shotgun.tools.barrel.label>
  <HRACA_Gun_Charge_Shotgun.verbs.Verb_Shoot.label>冲锋战术霰弹枪</HRACA_Gun_Charge_Shotgun.verbs.Verb_Shoot.label>
  <!-- EN: charge compact smg -->
  <HRACA_Gun_Charge_SMG.label>紧凑型冲锋枪</HRACA_Gun_Charge_SMG.label>
  <!-- EN: A compact quickfire charged-shot SMG. Perfect for close range use. Each shot is charged with unstable energy as it leaves the barrel. Released on impact, the charged energy greatly increases the damage done. -->
  <HRACA_Gun_Charge_SMG.description>紧凑型快速充能射击 SMG。非常适合近距离使用。每一发子弹在离开枪管时都会充满不稳定的能量。在撞击时释放，带电能量会大大增加造成的伤害。</HRACA_Gun_Charge_SMG.description>
  <HRACA_Gun_Charge_SMG.tools.stock.label>库存</HRACA_Gun_Charge_SMG.tools.stock.label>
  <HRACA_Gun_Charge_SMG.tools.barrel.label>桶</HRACA_Gun_Charge_SMG.tools.barrel.label>
  <HRACA_Gun_Charge_SMG.tools.grip.label>握把</HRACA_Gun_Charge_SMG.tools.grip.label>
  <HRACA_Gun_Charge_SMG.verbs.Verb_Shoot.label>紧凑型冲锋枪</HRACA_Gun_Charge_SMG.verbs.Verb_Shoot.label>
  <!-- EN: charge anti-materiel rifle -->
  <HRACA_Gun_Charge_Sniper.label>冲锋反器材步枪</HRACA_Gun_Charge_Sniper.label>
  <!-- EN: A charge shot, long ranged, sniper rifle. It cuts through armor like butter. Each shot is charged with unstable energy as it leaves the barrel. Released on impact, the charged energy greatly increases the damage done. -->
  <HRACA_Gun_Charge_Sniper.description>冲锋枪，远程狙击步枪。它能像黄油一样切开装甲。每一发子弹在离开枪管时都充满了不稳定的能量。在撞击时释放，带电能量会大大增加造成的伤害。</HRACA_Gun_Charge_Sniper.description>
  <HRACA_Gun_Charge_Sniper.tools.stock.label>库存</HRACA_Gun_Charge_Sniper.tools.stock.label>
  <HRACA_Gun_Charge_Sniper.tools.barrel.label>桶</HRACA_Gun_Charge_Sniper.tools.barrel.label>
  <HRACA_Gun_Charge_Sniper.tools.grip.label>握把</HRACA_Gun_Charge_Sniper.tools.grip.label>
  <HRACA_Gun_Charge_Sniper.verbs.Verb_Shoot.label>冲锋反器材步枪</HRACA_Gun_Charge_Sniper.verbs.Verb_Shoot.label>
</LanguageData>
